greenpak/__init__.py
greenpak/devices.py
greenpak/driver.py
greenpak/i2c.py
greenpak/py.typed
greenpak/utils.py
greenpak/data_files/README.md
greenpak/data_files/SLG46824_default.hex
greenpak/data_files/SLG46826_default.hex
greenpak/data_files/SLG46827_default.hex
greenpak/data_files/SLG47004_default.hex
greenpak/data_files/__init__.py
greenpak-0.0.30.dist-info/METADATA
greenpak-0.0.30.dist-info/WHEEL
greenpak-0.0.30.dist-info/licenses/LICENSE
greenpak-0.0.30.dist-info/RECORD
