Metadata-Version: 2.4
Name: greenpak
Version: 0.0.30
Summary: An easy to use Python API for programming and accessing Renesas's GreenPak SPLD devices.
Project-URL: Homepage, https://github.com/zapta/greenpak
Project-URL: Documentation, https://greenpak.readthedocs.io/en/latest/
Project-URL: Bug Tracker, https://github.com/zapta/greenpak/issues
Author-email: Zapta <zapta@zapta.com>
License-File: LICENSE
Classifier: License :: CC0 1.0 Universal (CC0 1.0) Public Domain Dedication
Classifier: Operating System :: OS Independent
Classifier: Programming Language :: Python :: 3
Requires-Python: >=3.7
Requires-Dist: hackpyratebus>=0.0.6
Requires-Dist: i2c-adapter>=0.0.4
Requires-Dist: i2cdriver>=1.0.1
Requires-Dist: intelhex>=2.3.0
Requires-Dist: smbus2==0.4.3
Requires-Dist: typing-extensions>=4.7.1
